{"key": {"kind": "UserMessage", "encoded": "ag1zfm1tLWFwaS1kZW1vchgLEgtVc2VyTWVzc2FnZRiAgICA-JaVCgw"}, "data": {"name": "Sam", "message": "Hi!", "email": null, "created": 1452795252, "modified": 1452795252}}
{"key": {"kind": "UserMessage", "encoded": "ag1zfm1tLWFwaS1kZW1vchgLEgtVc2VyTWVzc2FnZRiAgICA-MKECgw"}, "data": {"name": "Tim", "message": "Sup", "email": null, "created": 1452795252, "modified": 1452795252}}
{"key": {"kind": "UserMessage", "encoded": "ag1zfm1tLWFwaS1kZW1vchgLEgtVc2VyTWVzc2FnZRiAgICAgICACgw"}, "data": {"name": "Alex", "message": "Blabs", "email": null, "created": 1452795252, "modified": 1452795252}}
{"key": {"kind": "UserMessage", "encoded": "ag1zfm1tLWFwaS1kZW1vchgLEgtVc2VyTWVzc2FnZRiAgICA-MKECgw"}, "data": {"name": "Jan", "message": "Yeezy", "email": null, "created": 1452795252, "modified": 1452795252}}
{"key": {"kind": "UserMessage", "encoded": "ag1zfm1tLWFwaS1kZW1vchgLEgtVc2VyTWVzc2FnZRiAgICAgICACgw"}, "data": {"name": "Ryan", "message": "Yompin", "email": null, "created": 1452795252, "modified": 1452795252}}